exspy/__init__.py
exspy/_defaults_parser.py
exspy/_signal_tools.py
exspy/_utils.py
exspy/conftest.py
exspy/hyperspy_extension.yaml
exspy/material.py
exspy/_docstrings/__init__.py
exspy/_docstrings/model.py
exspy/_misc/__init__.py
exspy/_misc/elements.py
exspy/_misc/material.py
exspy/_misc/eds/__init__.py
exspy/_misc/eds/ffast_mac.py
exspy/_misc/eds/utils.py
exspy/_misc/eels/__init__.py
exspy/_misc/eels/base_gos.py
exspy/_misc/eels/eelsdb.py
exspy/_misc/eels/effective_angle.py
exspy/_misc/eels/electron_inelastic_mean_free_path.py
exspy/_misc/eels/gosh_gos.py
exspy/_misc/eels/hartree_slater_gos.py
exspy/_misc/eels/hydrogenic_gos.py
exspy/_misc/eels/tools.py
exspy/components/__init__.py
exspy/components/eels_arctan.py
exspy/components/eels_cl_edge.py
exspy/components/eels_double_power_law.py
exspy/components/eels_vignetting.py
exspy/components/pes_core_line_shape.py
exspy/components/pes_see.py
exspy/components/pes_voigt.py
exspy/components/volume_plasmon_drude.py
exspy/data/EDS_SEM_TM002.hspy
exspy/data/EDS_TEM_FePt_nanoparticles.hspy
exspy/data/__init__.py
exspy/misc/__init__.py
exspy/misc/elements.py
exspy/misc/material.py
exspy/misc/eds/__init__.py
exspy/misc/eds/utils.py
exspy/misc/eels/_init__.py
exspy/misc/eels/electron_inelastic_mean_free_path.py
exspy/misc/eels/tools.py
exspy/models/__init__.py
exspy/models/edsmodel.py
exspy/models/edssemmodel.py
exspy/models/edstemmodel.py
exspy/models/eelsmodel.py
exspy/signals/__init__.py
exspy/signals/dielectric_function.py
exspy/signals/eds.py
exspy/signals/eds_sem.py
exspy/signals/eds_tem.py
exspy/signals/eels.py
exspy/tests/__init__.py
exspy/tests/test_deprecated_import.py
exspy/tests/test_non-uniform_not-implemented.py
exspy/tests/components/__init__.py
exspy/tests/components/coreloss_spectrum.msa
exspy/tests/components/lowloss_spectrum.msa
exspy/tests/components/test_EELSarctan.py
exspy/tests/components/test_double_power_law.py
exspy/tests/components/test_eels_cl_edge.py
exspy-0.3.1.dist-info/LICENSE
exspy-0.3.1.dist-info/METADATA
exspy-0.3.1.dist-info/WHEEL
exspy-0.3.1.dist-info/entry_points.txt
exspy-0.3.1.dist-info/top_level.txt
exspy-0.3.1.dist-info/RECORD
