Metadata-Version: 2.1
Name: exspy
Version: 0.3.1
Summary: EELS and EDS analysis with the HyperSpy framework
License: GNU GENERAL PUBLIC LICENSE
Project-URL: Homepage, https://hyperspy.org/exspy
Project-URL: Bug Reports, https://github.com/hyperspy/exspy/issues
Project-URL: Source, https://github.com/hyperspy/exspy
Keywords: python,hyperspy,data analysis,microscopy,electron microscopy,electron energy loss spectroscopy,energy-dispersive X-ray spectroscopy,X-ray energy-dispersive spectroscopy,EELS,EDS,EDX,SEM,STEM,TEM
Classifier: Development Status :: 4 - Beta
Classifier: Intended Audience :: Developers
Classifier: Intended Audience :: Science/Research
Classifier: Topic :: Software Development :: Libraries
Classifier: Topic :: Scientific/Engineering
Classifier: Topic :: Scientific/Engineering :: Physics
Classifier: License :: OSI Approved :: GNU General Public License v3 (GPLv3)
Classifier: Operating System :: OS Independent
Classifier: Programming Language :: Python :: 3.8
Classifier: Programming Language :: Python :: 3.9
Classifier: Programming Language :: Python :: 3.10
Classifier: Programming Language :: Python :: 3.11
Classifier: Programming Language :: Python :: 3.12
Requires-Python: >=3.8
License-File: LICENSE
Requires-Dist: dask[array]
Requires-Dist: hyperspy>=2.0rc0
Requires-Dist: matplotlib
Requires-Dist: numpy
Requires-Dist: pint
Requires-Dist: pooch
Requires-Dist: prettytable
Requires-Dist: requests
Requires-Dist: scipy
Requires-Dist: traits
Provides-Extra: all
Requires-Dist: exspy[gui-jupyter]; extra == "all"
Requires-Dist: exspy[gui-traitsui]; extra == "all"
Requires-Dist: exspy[speed]; extra == "all"
Provides-Extra: dev
Requires-Dist: ruff; extra == "dev"
Provides-Extra: doc
Requires-Dist: numpydoc; extra == "doc"
Requires-Dist: pydata-sphinx-theme>=0.13; extra == "doc"
Requires-Dist: sphinx; extra == "doc"
Requires-Dist: sphinx-copybutton; extra == "doc"
Requires-Dist: sphinx-design; extra == "doc"
Requires-Dist: sphinx-favicon; extra == "doc"
Requires-Dist: sphinx-gallery; extra == "doc"
Requires-Dist: sphinxcontrib-towncrier; extra == "doc"
Requires-Dist: towncrier<24; extra == "doc"
Provides-Extra: gui-jupyter
Requires-Dist: hyperspy-gui-ipywidgets>=2.0; extra == "gui-jupyter"
Provides-Extra: gui-traitsui
Requires-Dist: hyperspy-gui-traitsui>=2.0; extra == "gui-traitsui"
Provides-Extra: speed
Requires-Dist: numexpr; extra == "speed"
Provides-Extra: tests
Requires-Dist: pytest>=5.0; extra == "tests"
Requires-Dist: pytest-mpl; extra == "tests"
Requires-Dist: pytest-cov>=2.8.1; extra == "tests"
Requires-Dist: pytest-xdist; extra == "tests"
Requires-Dist: setuptools-scm; extra == "tests"
